<?xml version="1.0" encoding="UTF-8"?>
<!-- Chinese FBReaderJ resources, by http://shucang.com/ -->
<resources>
	<node name="library" value="FBReader 书库" >
		<node name="unknownAuthor" value="佚名" />
		<node name="booksWithNoTags" value="未归类" />
		<node name="demo" value="试读本" />
		<node name="byAuthor" value="作者">
			<node name="summary" value="按作者排序" />
		</node>
		<node name="byTitle" value="按书名" >
			<node name="summary" value="按书名排序" />
		</node>
		<node name="bySeries" value="按系列" >
			<node name="summary" value="按系列排序" />
		</node>
		<node name="byTag" value="标签">
			<node name="summary" value="按标签排序"/>
		</node>
		<node name="recent" value="最近读过">
			<node name="summary" value="最近读过的书刊"/>
		</node>
		<node name="favorites" value="超爱的书">
			<node name="summary" value="很喜欢的，特地收藏起来的书刊"/>
		</node>
		<node name="found" value="搜索结果">
			<node name="summary" value="搜索结果: %s" />
		</node>
		<node name="fileTree" value="文件夹">
			<node name="summary" value="浏览各级文件夹"/>
		</node>
		<node name="fileTreeRoot" value="本地设备">
			<node name="summary" value="设备上的文件夹"/>
		</node>
		<node name="fileTreeCard" value="SD存储卡">
			<node name="summary" value="插入设备的存储卡"/>
		</node>
		<node name="fileTreeLibrary" value="FBReader 文件夹">
			<node name="summary" value="FBReader 存放书刊的文件夹"/>
		</node>
		<node name="menu">
			<node name="localSearch" value="本地搜索" />
		</node>
		<node name="openBook" value="打开阅读" />
		<node name="showBookInfo" value="书文信息"/>
		<node name="shareBook" value="Share book" toBeTranslated="true"/>
		<node name="deleteBook" value="删除本书" />
		<node name="addToFavorites" value="收藏到我的超爱"/>
		<node name="removeFromFavorites" value="从收藏列表中移除"/>
	</node>
	<node name="networkLibrary" value="FBReader 网络书库" >
		<node name="byAuthor" value="作者">
			<node name="summary" value="按作者排序" />
		</node>
		<node name="byTitle" value="按书名" >
			<node name="summary" value="按书名排序" />
		</node>
		<node name="byDate" value="按日期" >
			<node name="summary" value="按购买日期排序" />
		</node>
		<node name="bySeries" value="按系列" >
			<node name="summary" value="按系列排序" />
		</node>
		<node name="search" value="搜索">
			<node name="summary" value="在 %s 上搜索图书" />
			<node name="summaryAllCatalogs" value="搜索书库" />
			<node name="summaryInProgress" value="搜索中..." />
		</node>
		<node name="found" value="搜索结果">
			<node name="summary" value="搜索结果: %s" />
		</node>
		<node name="openCatalog" value="打开书库" />
		<node name="networkSearch" value="搜索"/>
		<node name="showResults" value="显示结果"/>
		<node name="showBooks" value="显示书籍"/>
		<node name="download" value="下载" />
		<node name="read" value="阅读" />
		<node name="delete" value="删除" />
		<node name="readDemo" value="试读" />
		<node name="deleteDemo" value="删除试读本" />
		<node name="downloadDemo" value="下载试读本" />
		<node name="buy" value="购买(%s)" />
		<node name="addToBasket" value="添加到购物篮" />
		<node name="removeFromBasket" value="从购物篮中删除" />
		<node name="openBasket" value="打开购物篮" />
		<node name="clearBasket" value="清空购物篮" />
		<node name="buyAllBooks" value="购买所有书籍" />
		<node name="openInBrowser" value="在浏览器中打开" />
		<node name="stopLoading" value="停止加载" />
		<node name="stopSearching" value="停止搜索" />
		<node name="signIn" value="登录"/>
		<node name="signOut" value="退出 (%s)"/>
		<node name="topup" value="重新输入账号(目前: %s)" />
		<node name="topupTitle" value="重新输入账号"/>
		<node name="topupViaBrowser" value="在浏览器中打开页面"/>
		<node name="authorizationMenuTitle" value="选择操作" />
		<node name="topupSummary" value="当前: %s"/>
		<node name="basket" value="购物篮" />
		<node name="basketSummaryEmpty" value="没有书籍" />
		<node name="basketSummaryCountOnly" value="%0 本书" />
		<node name="basketSummary" value="%0 本书 (%1)"/>
		<node name="alreadyDownloading" value="正在下载" />
		<node name="alreadyDownloadingDemo" value="正在下载试读本" />
		<node name="stoppingCatalogLoading" value="停止加载" />
		<node name="stoppingNetworkSearch" value="停止搜索" />
		<node name="editCustomCatalog" value="编辑书库目录"/>
		<node name="removeCustomCatalog" value="移除书库"/>
		<node name="addCustomCatalog" value="增加书库"/>
		<node name="addCustomCatalogSummary" value="手工添加自有的OPDS书库"/>
		<node name="confirmQuestions">
			<node name="read" value="是否本地阅读" />
			<node name="download" value="是否下载本图书?" />
			<node name="readDemo" value="是否试读?" />
			<node name="downloadDemo" value="是否下载试读本?" />
			<node name="buy" value="是否购买本书? (%s)" />
			<node name="openInBrowser" value="是否在浏览器中打开?" />
		</node>
		<node name="downloadingCatalogs" value="书库目录下载" /> <!-- used as notification title -->
		<node name="searchingNetwork" value="搜索书库"/> <!-- used as notification title -->
		<node name="addCatalog">
			<node name="title" value="Add catalog" toBeTranslated="true"/>
			<node name="editUrl" value="Enter URL manually" toBeTranslated="true"/>
		</node>
		<node name="menu">
			<node name="networkSearch" value="网络搜索" />
			<node name="reload" value="重新加载" />
			<node name="signIn" value="登录"/>
			<node name="signUp" value="注册" />
			<node name="signOut" value="退出 (%s)"/>
			<node name="topup" value="重新输入账号"/>
			<node name="addCustomCatalog" value="添加书库"/>
			<node name="refreshCatalogsList" value="刷新书库"/>
			<node name="languages" value="语言过滤"/>
			<node name="clearBasket" value="清空购物篮" />
			<node name="buyAllBooks" value="购买所有图书" />
		</node>
	</node>
	<node name="buyBook">
		<node name="title" value="购买书籍" />
		<node name="titleSeveralBooks" value="购买书籍" />
		<node name="confirm" value="确认购买%s书籍?" />
		<node name="confirmSeveralBooks" value="确认购买%s书籍?" />
		<node name="alreadyBought" value="该书已经买过" />
		<node name="notAuthorized" value="需要授权" />
		<node name="noAccountInformation" value="无法加载账号状态" />
		<node name="unsufficientFunds" value="你这次买了 %0 ，但是你现在只有 %1" />
		<node name="zeroFunds" value="你这次买了 %0" />
	</node>
	<node name="bookInfo">
		<node name="bookInfo" value="书籍信息" />
		<node name="fileInfo" value="书文信息" />
		<node name="description" value="描述" />
		<node name="noDescription" value="没有有效描述." />
		<node name="annotation" value="简介" />
		<node name="title" value="书名:" />
		<node name="authors" value="作者:" />
		<node name="series" value="丛书系列:" />
		<node name="indexInSeries" value="系列序号:" />
		<node name="tags" value="标签:" />
		<node name="language" value="语言:" />
		<node name="name" value="文件名:" />
		<node name="type" value="类型:" />
		<node name="size" value="大小:" />
		<node name="time" value="最后更改时间:" />
		<node name="sizeInBytes" value="%s 字节" />
		<node name="sizeInKiloBytes" value="%s kB" />
		<node name="catalog" value="书库:" />
		<node name="extraLinks" value="相关链接" />
		<node name="menu">
			<node name="edit" value="编辑" />
		</node>
	</node>
	<node name="bookDownloader">
		<node name="tickerSuccess" value="下载成功" />
		<node name="tickerError" value="下载出错" />
		<node name="contentSuccess" value="下载完成" />
		<node name="contentError" value="下载失败" />
		<node name="downloadingStarted" value="开始下载" />
		<node name="alreadyDownloading" value="已在下载" />
		<node name="cannotCreateDirectory" value="无法创建文件夹 %s" />
		<node name="cannotCreateFile" value="无法创建文件 %s" />
	</node>
	<node name="tocView">
		<node name="expandTree" value="展开目录" />
		<node name="collapseTree" value="折叠目录" />
		<node name="readText" value="阅读图书内容" />
	</node>
	<node name="bookmarksView">
		<node name="thisBook" value="本书" />
		<node name="allBooks" value="所有图书" />
		<node name="found" value="搜索结果" />
		<node name="new" value="添加书签" />
		<node name="open" value="打开书签" />
		<node name="edit" value="编辑书签" />
		<node name="delete" value="删除书签" />
		<node name="menu">
			<node name="search" value="搜索" />
		</node>
	</node>
	<node name="cancelMenu">
		<node name="library" value="Open library" toBeTranslated="true"/>
		<node name="networkLibrary" value="Open network library" toBeTranslated="true"/>
		<node name="previousBook" value="打开上一本书" />
		<node name="returnTo" value="返回到..." />
		<node name="back" value="后退" />
		<node name="forward" value="前进" />
		<node name="close" value="关闭FBReader" />
	</node>
	<node name="selection" value="选择">
		<node name="copyToClipboard" value="复制到剪贴板" />
		<node name="openInDictionary" value="打开字典" />
		<node name="quoteFrom" value="从%s中引用" />
		<node name="textInBuffer" value="复制到剪贴板:&#10;%s" />
		<node name="bookmarkCreated" value="创建书签:&#10;%s" />
		<node name="clearSelection" value="清除" />
	</node>
	<node name="menu">
		<node name="preferences" value="设置" />
		<node name="bookInfo" value="书籍信息" />
		<node name="library" value="本地书柜" />
		<node name="toc" value="本书目录" />
		<node name="day" value="白天" />
		<node name="night" value="夜间" />
		<node name="networkLibrary" value="在线书库" />
		<node name="navigate" value="进度跳转">
			<node name="toc" value="内容目录" />
			<node name="gotoHome" value="翻到图书开始" />
			<node name="gotoPageNumber" value="翻到页码" />
			<node name="gotoSectionStart" value="翻到章节开始" />
			<node name="gotoSectionEnd" value="翻到章节结束" />
			<node name="nextTOCSection" value="翻到下一章节 " />
			<node name="previousTOCSection" value="翻到上一章节" />
			<node name="undo" value="还原" />
			<node name="redo" value="重做" />
        </node>
        <node name="light" value="亮度"/>
		<node name="shareBook" value="Share book" toBeTranslated="true"/>
		<node name="search" value="搜索" />
        <node name="showfont" value = "字体调整"/>
        <node name="showlight" value = "亮度调节"/>
		<node name="toggleFullscreen" value="全屏" />
        <node name="bookmarks" value="目录/书签" />
        <node name="selectionBookmark" value="添加书签" />
	</node>
	<node name="dialog">
		<node name="button">
			<node name="install" value="安装" />
			<node name="update" value="更新" />
			<node name="skip" value="跳过" />
			<node name="buy" value="购买" />
			<node name="buyAndDownload" value="购买并下载" />
			<node name="continue" value="继续" />
			<node name="editUrl" value="编辑 URL" />
			<node name="tryAgain" value="再次尝试" />
			<node name="openBook" value="阅读" />
			<node name="editInfo" value="编辑" />
			<node name="reloadInfo" value="重新加载" />
			<node name="shareBook" value="Share" toBeTranslated="true"/>
			<node name="topup" value="重新输入账号"/>
			<node name="pay" value="支付" />
			<node name="refresh" value="刷新" />
			<node name="authorize" value="授权" />
			<node name="resetPosition" value="Reset position" toBeTranslated="true"/>
			<node name="sendReport" value="Send report" toBeTranslated="true"/>
		</node>
		<node name="plugin">
			<node name="installTitle" value="安装插件" />
			<node name="updateTitle" value="更新插件" />
			<node name="dontAskAgain" value="别再问了" />
		</node>
		<node name="installDictionary">
			<node name="title" value="安装字典" />
			<node name="message" value="你希望安装 %s 么?" />
		</node>
		<node name="BookInfo">
			<node name="fileName" value="文件" />
			<node name="title" value="书名" />
			<node name="language" value="语言" />
			<node name="encoding" value="编码" />
		</node>
		<node name="Preferences">
			<node name="directories" value="文件夹设定">
				<node name="summary" value="相关文件夹位置设定"/>
				<node name="books" value="书文存放位置"/>
				<node name="fonts" value="字体存放位置"/>
				<node name="wallpapers" value="墙纸存放位置" />
			</node>
			<node name="appearance" value="屏幕显示">
                <node name="summary" value="自动休眠时间,屏幕方向等"/>
                <node name="turnOffTime" value="自动关闭屏幕时间">
                    <node name="default" value="系统默认"/>
                    <node name="1" value="1 分钟"/>
                    <node name="2" value="2 分钟"/>
                    <node name="3" value="3 分钟"/>
                    <node name="5" value="5 分钟"/>
                    <node name="10" value="10 分钟"/>
                    <node name="30" value="30 分钟"/>
                    <node name="never" value="常亮"/>
                </node>
                <node name="screenOrientation" value="屏幕方向">
                   	<node name="portrait" value="竖屏"/>
	                <node name="landscape" value="横屏"/> 
	                <node name="system" value="自动"/> 
                </node>
			</node>
			<node name="text" value="文字排版">
				<node name="summary" value="字体排版,页面边距,对齐,断字等"/>
				<node name="fontProperties" value="Font properties" toBeTranslated="true">
					<node name="summary" value="Font smoothing options" toBeTranslated="true"/>
					<node name="antiAlias" value="Antialiasing" toBeTranslated="true">
						<node name="summaryOn" value="Antialiasing is enabled" toBeTranslated="true"/>
						<node name="summaryOff" value="Antialiasing is disabled" toBeTranslated="true"/>
					</node>
					<node name="deviceKerning" value="Device kerning" toBeTranslated="true">
						<node name="summaryOn" value="Device kerning is enabled" toBeTranslated="true"/>
						<node name="summaryOff" value="Device kerning is disabled" toBeTranslated="true"/>
					</node>
					<node name="dithering" value="Dithering" toBeTranslated="true">
						<node name="summaryOn" value="Color dithering is enabled" toBeTranslated="true"/>
						<node name="summaryOff" value="Color dithering is disabled" toBeTranslated="true"/>
					</node>
					<node name="hinting" value="Hinting" toBeTranslated="true">
						<node name="summaryOn" value="Font hinting is enabled" toBeTranslated="true"/>
						<node name="summaryOff" value="Font hinting is disabled" toBeTranslated="true"/>
					</node>
					<node name="subpixel" value="Subpixel smoothing" toBeTranslated="true">
						<node name="summaryOn" value="Subpixel smoothing is enabled" toBeTranslated="true"/>
						<node name="summaryOff" value="Subpixel smoothing is disabled" toBeTranslated="true"/>
					</node>
				</node>
				<node name="font" value="字体">
					<node name="unchanged" value="&lt;不变&gt;" />
				</node>
				<node name="fontSize" value="字体大小"/>
				<node name="fontSizeDifference" value="大小差异" />
				<node name="fontStyle" value="字型">
					<node name="regular" value="正常"/>
					<node name="bold" value="加粗"/>
					<node name="italic" value="倾斜"/>
					<node name="boldItalic" value="加粗并倾斜"/>
				</node>
				<node name="bold" value="加粗">
					<node name="summaryOn" value="加粗"/>
					<node name="summaryOff" value="正常"/>
					<node name="unchanged" value="&lt;不变&gt;" />
				</node>
				<node name="italic" value="倾斜">
					<node name="summaryOn" value="倾斜"/>
					<node name="summaryOff" value="规则"/>
					<node name="unchanged" value="&lt;不变&gt;" />
				</node>
				<node name="underlined" value="Underlined" toBeTranslated="true">
					<node name="summaryOn" value="underlined" toBeTranslated="true"/>
					<node name="summaryOff" value="regular" toBeTranslated="true"/>
					<node name="unchanged" value="&lt;不变&gt;" />
				</node>
				<node name="strikedThrough" value="Striked through" toBeTranslated="true">
					<node name="summaryOn" value="striked through" toBeTranslated="true"/>
					<node name="summaryOff" value="regular" toBeTranslated="true"/>
					<node name="unchanged" value="&lt;不变&gt;" />
				</node>
				<node name="lineSpacing" value="行间距">
					<node name="unchanged" value="&lt;不变&gt;" />
				</node>
				<node name="alignment" value="对齐">
					<node name="left" value="左" />
					<node name="right" value="右" />
					<node name="center" value="居中" />
					<node name="justify" value="对齐" />
					<node name="unchanged" value="&lt;不变&gt;" />
                </node>
                
				<node name="left" value="左边距" />
				<node name="right" value="右边距" />
				<node name="top" value="顶边距" />
				<node name="bottom" value="底边距" />
                
                <node name="autoHyphenations" value="自动断字">
					<node name="summaryOn" value="自动断字"/>
					<node name="summaryOff" value="禁止自动断字"/>
				</node>
				<node name="allowHyphenations" value="允许断字">
					<node name="summaryOn" value="断字"/>
					<node name="summaryOff" value="禁止断字"/>
					<node name="unchanged" value="&lt;不变&gt;" />
				</node>
				<node name="firstLineIndent" value="首行缩进" />
				<node name="spaceBefore" value="段前距" />
				<node name="spaceAfter" value="段后距" />
				<node name="leftIndent" value="左缩进" />
				<node name="rightIndent" value="右缩进" />
				<node name="more" value="更多样式">
					<node name="summary" value="分别设定标题、段落等."/>
					<node name="Regular Paragraph" value="连续段落" >
						<node name="summary" value=""/>
					</node>
					<node name="Title" value="书名" >
						<node name="summary" value=""/>
					</node>
					<node name="Section Title" value="章节标题" >
						<node name="summary" value=""/>
					</node>
					<node name="Poem Title" value="诗标题" >
						<node name="summary" value=""/>
					</node>
					<node name="Subtitle" value="副标题" >
						<node name="summary" value=""/>
					</node>
					<node name="Annotation" value="摘要" >
						<node name="summary" value=""/>
					</node>
					<node name="Epigraph" value="题词" >
						<node name="summary" value=""/>
					</node>
					<node name="Stanza" value="节" >
						<node name="summary" value=""/>
					</node>
					<node name="Verse" value="韵文" >
						<node name="summary" value=""/>
					</node>
					<node name="Preformatted text" value="预置格式文本" >
						<node name="summary" value=""/>
					</node>
					<node name="Image" value="图像" >
						<node name="summary" value=""/>
					</node>
					<node name="Cite" value="举例" >
						<node name="summary" value=""/>
					</node>
					<node name="Author" value="作者" >
						<node name="summary" value=""/>
					</node>
					<node name="Date" value="日期" >
						<node name="summary" value=""/>
					</node>
					<node name="Internal Hyperlink" value="内部超链接" >
						<node name="summary" value=""/>
					</node>
					<node name="Footnote" value="脚注" >
						<node name="summary" value=""/>
					</node>
					<node name="Emphasis" value="重点" >
						<node name="summary" value=""/>
					</node>
					<node name="Strong" value="固定" >
						<node name="summary" value=""/>
					</node>
					<node name="Subscript" value="下标" >
						<node name="summary" value=""/>
					</node>
					<node name="Superscript" value="上标" >
						<node name="summary" value=""/>
					</node>
					<node name="Code" value="编码" >
						<node name="summary" value=""/>
					</node>
					<node name="StrikeThrough" value="删除线" >
						<node name="summary" value=""/>
					</node>
					<node name="Italic" value="倾斜" >
						<node name="summary" value=""/>
					</node>
					<node name="Bold" value="加粗" >
						<node name="summary" value=""/>
					</node>
					<node name="Definition" value="定义" >
						<node name="summary" value=""/>
					</node>
					<node name="Definition Description" value="定义描述" >
						<node name="summary" value=""/>
					</node>
					<node name="Header 1" value="标题 1" >
						<node name="summary" value=""/>
					</node>
					<node name="Header 2" value="标题 2" >
						<node name="summary" value=""/>
					</node>
					<node name="Header 3" value="标题 3" >
						<node name="summary" value=""/>
					</node>
					<node name="Header 4" value="标题 4" >
						<node name="summary" value=""/>
					</node>
					<node name="Header 5" value="标题 5" >
						<node name="summary" value=""/>
					</node>
					<node name="Header 6" value="标题 6" >
						<node name="summary" value=""/>
					</node>
					<node name="External Hyperlink" value="外部链接" >
						<node name="summary" value=""/>
					</node>
				</node>
			</node>
			<node name="colors" value="颜色 &amp; 壁纸" >
				<node name="summary" value="设置文字颜色和背景壁纸"/>
				<node name="background" value="背景壁纸">
					<node name="solidColor" value="单色" />
					<node name="leather" value="皮革" />
					<node name="sepia" value="棕褐" />
                    <node name="wood" value="木质" />
                    <node name="read_bg_1" value="羊皮纸" />
                    <node name="read_bg_2" value="粉红回忆" />
                    <node name="read_bg_3" value="蓝色幻想" />
                    <node name="read_bg_6" value="咖啡时光" />
                    <node name="read_bg_7" value="水墨江南" />
				</node>
				<node name="backgroundColor" value="单色背景色" />
				<node name="selectionBackground" value="选择背景色" />
				<node name="selectionForeground" value="选择的文本" />
				<node name="text" value="普通文字" />
				<node name="hyperlink" value="链接文字" />
				<node name="hyperlinkVisited" value="已访问过的链接文字" />
				<node name="highlighting" value="搜索结果背景" />
				<node name="footer" value="页脚"/>
			</node>
			<node name="scrolling" value="翻页效果">
				<node name="summary" value="翻页动画特效"/>
				<node name="animation" value="动画效果" >
					<node name="none" value="无动画效果" />
					<node name="shift" value="左右滑动" />
					<node name="curl" value="拟真翻页" />
					<node name="curl3d" value="3D翻页" />
				</node>
				<node name="animationSpeed" value="动画速度" >
					<node name="fast" value="快" />
					<node name="slow" value="慢" />
				</node>
			</node>
			<node name="dictionary" value="字典设定">
				<node name="summary" value="设置字典及其对应操作"/>
				<node name="dictionary" value="字典"/>
				<node name="translator" value="译者" />
				<node name="tappingAction" value="长按动作设定">
					<node name="doNothing" value="长按不做任何事"/>
					<node name="selectSingleWord" value="长按选择词语"/>
					<node name="startSelecting" value="长按选择内容" />
					<node name="openDictionary" value="长按选择词语，放开后打开字典"/>
				</node>
				<node name="navigateOverAllWords" value="导航键访问词句设定">
					<node name="summaryOn" value="导航键访问所有的词句"/>
					<node name="summaryOff" value="导航键仅访问超链接词句"/>
				</node>
			</node>
		</node>
		<node name="deleteBookBox">
			<node name="message" value="确认删除该文件?" />
		</node>
		<node name="redownloadFileBox">
			<node name="message" value="该文件已存在，确认重新下载?" />
		</node>
		<node name="waitMessage">
			<node name="downloadingFile" value="已下载 %s" />
			<node name="search" value="搜索中，请等待..." />
			<node name="loadInfo" value="信息加载中，请等待..." />
			<node name="loadingBook" value="图书加载中，请等待..." />
			<node name="loadingBookList" value="书库加载中，请等待..." />
			<node name="creatingBooksDatabase" value="正在创建图书数据库，请等待..." />
			<node name="updatingBooksDatabase" value="正在更新图书数据库，请等待..." />
			<node name="loadingNetworkLibrary" value="正在打开书库，请等待..." />
			<node name="authentication" value="验证中.请等待..." />
			<node name="signOut" value="退出. 正在处理,请稍等..." />
			<node name="purchaseBook" value="书籍购买中. 请等待..." />
			<node name="loadingCatalogInfo" value="加载书库信息中，请稍待..." />
			<node name="loadingNetworkBookInfo" value="书籍信息加载中，请等待&#8230;"  />
			<node name="updatingCatalogsList" value="更新书库列表中，请稍待..."/>
			<node name="updatingAccountInformation" value="正在更新账户信息，请等待&#8230;" />
		</node>
		<node name="networkError">
			<node name="internalError" value="内部服务器出错" />
			<node name="purchaseNotEnoughMoney" value="金额不足" />
			<node name="purchaseMissingBook" value="图书缺失" />
			<node name="purchaseAlreadyPurchased" value="已购买书籍" />
			<node name="bookNotPurchased" value="未购买书籍" />
			<node name="downloadLimitExceeded" value="超过下载限制" />
			<node name="noUserEmail" value="你的电子邮箱可以注册&#10;" />
			<node name="unsupportedOperation" value="非法操作" />
			<node name="notAnOPDS" value="没有OPDS书库" />
			<node name="noRequiredInformation" value="书库目录中必须的信息没有定义" />
			<node name="cacheDirectoryError" value="无法创建缓存目录" />
		</node>
		<node name="AuthenticationDialog">
			<node name="title" value="鉴定" />
			<node name="unencryptedWarning" value="你的密码将明文传送" />
			<node name="login" value="登录" />
			<node name="password" value="密码" />
			<node name="loginIsEmpty" value="用户名不允许为空" />
			<node name="register" value="注册" />
		</node>
		<node name="CustomCatalogDialog">
			<node name="title" value="FBReader: 添加自设书库"  />
			<node name="catalogTitle" value="书库名称" />
			<node name="catalogUrl" value="书库网址" />
			<node name="catalogSummary" value="简介" />
			<node name="catalogTitleExample" value="例如: 古滕堡项目书库目录" />
			<node name="catalogUrlExample" value="例如: http://m.gutenberg.org/" />
			<node name="catalogSummaryExample" value="例如: 公版图书" />
			<node name="titleIsEmpty" value="名称不能为空" />
			<node name="urlIsEmpty" value="书库网址不能为空" />
			<node name="invalidUrl" value="无效的URL地址" />
			<node name="titleAlreadyExists" value="该名称已经在用" />
			<node name="siteAlreadyExists" value="该书库已经在用" />
		</node>
	</node>
	<node name="errorMessage">
		<node name="cannotRunAndroidMarket" value="无法访问Android官方应用市场. 请手工安装 %s ."/>
		<node name="textNotFound" value="对不起，本书中找不到对应内容" />
		<node name="bookNotFound" value="对不起，书库中找不到需要的书籍" />
		<node name="bookmarkNotFound" value="对不起，找不到对应的书签" />
		<node name="cannotOpenBook" value="对不起，无法开启本书" />
		<node name="dictionaryIsNotInstalled" value="抱歉，你没有安装字典."/>
		<node name="permissionDenied" value="对不起，没有权限"/>
		<node name="noFavorites" value="对不起，你的收藏列表为空"/>
		<node name="emptyCatalog" value="空书库目录"/>
		<node name="emptyBasket" value="很抱歉，你的购物篮是空的" />
		<node name="emptyNetworkSearchResults" value="没有找到对应的书籍"/>
	</node>
	<node name="external">
		<node name="browser" value="浏览器" />
		<node name="defaultBrowser" value="默认浏览器" />
	</node>
	<node name="mobipocketPlugin">
		<node name="unknown" value="未知的错误" />
		<node name="unsupportedCompressionMethod" value="不支持的压缩方法" />
		<node name="encryptedFile" value="受版权保护文件" />
	</node>
	<node name="crash">
		<node name="fixBooksDirectory">
			<node name="title" value="Directory issue" toBeTranslated="true"/>
			<node name="text" value="缓存目录无法写入，或许你忘了插入或已拔出内存卡。请处理这个问题，或者进入下面的另一个文件夹。" />
		</node>
	</node>
	<node name="error">
		<node name="bookReading">
			<node name="title" value="FBReader issue" toBeTranslated="true"/>
		</node>
	</node>
	<node name="bookReadingException">
		<node name="errorReadingFile" value="Error occured during reading '%s'" toBeTranslated="true"/>
		<node name="errorReadingZip" value="Error occured during extracting '%s'" toBeTranslated="true"/>
		<node name="pluginNotFound" value="No plugin for '%s'" toBeTranslated="true"/>
		<node name="unknownPluginType" value="Unknown plugin type: %s" toBeTranslated="true"/>
		<node name="fileNotFound" value="File is not found: %s" toBeTranslated="true"/>
		<node name="opfFileNotFound" value="OPF is not found in %s" toBeTranslated="true"/>
		<node name="unsupportedFileFormat" value="File format is not supported for '%s'" toBeTranslated="true"/>
		<node name="errorParsingRtf" value="Rtf parsing error in: %s" toBeTranslated="true"/>
	</node>
</resources>
